{"paths": {"admin/js/vendor/select2/i18n/af.js": "admin/js/vendor/select2/i18n/af.4f6fcd73488c.js", "admin/js/vendor/select2/i18n/ar.js": "admin/js/vendor/select2/i18n/ar.65aa8e36bf5d.js", "admin/js/vendor/select2/i18n/az.js": "admin/js/vendor/select2/i18n/az.270c257daf81.js", "admin/js/vendor/select2/i18n/bg.js": "admin/js/vendor/select2/i18n/bg.39b8be30d4f0.js", "admin/js/vendor/select2/i18n/bn.js": "admin/js/vendor/select2/i18n/bn.6d42b4dd5665.js", "admin/js/vendor/select2/i18n/bs.js": "admin/js/vendor/select2/i18n/bs.91624382358e.js", "admin/js/vendor/select2/i18n/ca.js": "admin/js/vendor/select2/i18n/ca.a166b745933a.js", "admin/js/vendor/select2/i18n/cs.js": "admin/js/vendor/select2/i18n/cs.4f43e8e7d33a.js", "admin/js/vendor/select2/i18n/da.js": "admin/js/vendor/select2/i18n/da.766346afe4dd.js", "admin/js/vendor/select2/i18n/de.js": "admin/js/vendor/select2/i18n/de.8a1c222b0204.js", "admin/js/vendor/select2/i18n/dsb.js": "admin/js/vendor/select2/i18n/dsb.56372c92d2f1.js", "admin/js/vendor/select2/i18n/el.js": "admin/js/vendor/select2/i18n/el.27097f071856.js", "admin/js/vendor/select2/i18n/en.js": "admin/js/vendor/select2/i18n/en.cf932ba09a98.js", "admin/js/vendor/select2/i18n/es.js": "admin/js/vendor/select2/i18n/es.66dbc2652fb1.js", "admin/js/vendor/select2/i18n/et.js": "admin/js/vendor/select2/i18n/et.2b96fd98289d.js", "admin/js/vendor/select2/i18n/eu.js": "admin/js/vendor/select2/i18n/eu.adfe5c97b72c.js", "admin/js/vendor/select2/i18n/fa.js": "admin/js/vendor/select2/i18n/fa.3b5bd1961cfd.js", "admin/js/vendor/select2/i18n/fi.js": "admin/js/vendor/select2/i18n/fi.614ec42aa9ba.js", "admin/js/vendor/select2/i18n/fr.js": "admin/js/vendor/select2/i18n/fr.05e0542fcfe6.js", "admin/js/vendor/select2/i18n/gl.js": "admin/js/vendor/select2/i18n/gl.d99b1fedaa86.js", "admin/js/vendor/select2/i18n/he.js": "admin/js/vendor/select2/i18n/he.e420ff6cd3ed.js", "admin/js/vendor/select2/i18n/hi.js": "admin/js/vendor/select2/i18n/hi.70640d41628f.js", "admin/js/vendor/select2/i18n/hr.js": "admin/js/vendor/select2/i18n/hr.a2b092cc1147.js", "admin/js/vendor/select2/i18n/hsb.js": "admin/js/vendor/select2/i18n/hsb.fa3b55265efe.js", "admin/js/vendor/select2/i18n/hu.js": "admin/js/vendor/select2/i18n/hu.6ec6039cb8a3.js", "admin/js/vendor/select2/i18n/hy.js": "admin/js/vendor/select2/i18n/hy.c7babaeef5a6.js", "admin/js/vendor/select2/i18n/id.js": "admin/js/vendor/select2/i18n/id.04debded514d.js", "admin/js/vendor/select2/i18n/is.js": "admin/js/vendor/select2/i18n/is.3ddd9a6a97e9.js", "admin/js/vendor/select2/i18n/it.js": "admin/js/vendor/select2/i18n/it.be4fe8d365b5.js", "admin/js/vendor/select2/i18n/ja.js": "admin/js/vendor/select2/i18n/ja.170ae885d74f.js", "admin/js/vendor/select2/i18n/ka.js": "admin/js/vendor/select2/i18n/ka.2083264a54f0.js", "admin/js/vendor/select2/i18n/km.js": "admin/js/vendor/select2/i18n/km.c23089cb06ca.js", "admin/js/vendor/select2/i18n/ko.js": "admin/js/vendor/select2/i18n/ko.e7be6c20e673.js", "admin/js/vendor/select2/i18n/lt.js": "admin/js/vendor/select2/i18n/lt.23c7ce903300.js", "admin/js/vendor/select2/i18n/lv.js": "admin/js/vendor/select2/i18n/lv.08e62128eac1.js", "admin/js/vendor/select2/i18n/mk.js": "admin/js/vendor/select2/i18n/mk.dabbb9087130.js", "admin/js/vendor/select2/i18n/ms.js": "admin/js/vendor/select2/i18n/ms.4ba82c9a51ce.js", "admin/js/vendor/select2/i18n/nb.js": "admin/js/vendor/select2/i18n/nb.da2fce143f27.js", "admin/js/vendor/select2/i18n/ne.js": "admin/js/vendor/select2/i18n/ne.3d79fd3f08db.js", "admin/js/vendor/select2/i18n/nl.js": "admin/js/vendor/select2/i18n/nl.997868a37ed8.js", "admin/js/vendor/select2/i18n/pl.js": "admin/js/vendor/select2/i18n/pl.6031b4f16452.js", "admin/js/vendor/select2/i18n/ps.js": "admin/js/vendor/select2/i18n/ps.38dfa47af9e0.js", "admin/js/vendor/select2/i18n/pt-BR.js": "admin/js/vendor/select2/i18n/pt-BR.e1b294433e7f.js", "admin/js/vendor/select2/i18n/pt.js": "admin/js/vendor/select2/i18n/pt.33b4a3b44d43.js", "admin/js/vendor/select2/i18n/ro.js": "admin/js/vendor/select2/i18n/ro.f75cb460ec3b.js", "admin/js/vendor/select2/i18n/ru.js": "admin/js/vendor/select2/i18n/ru.934aa95f5b5f.js", "admin/js/vendor/select2/i18n/sk.js": "admin/js/vendor/select2/i18n/sk.33d02cef8d11.js", "admin/js/vendor/select2/i18n/sl.js": "admin/js/vendor/select2/i18n/sl.131a78bc0752.js", "admin/js/vendor/select2/i18n/sq.js": "admin/js/vendor/select2/i18n/sq.5636b60d29c9.js", "admin/js/vendor/select2/i18n/sr-Cyrl.js": "admin/js/vendor/select2/i18n/sr-Cyrl.f254bb8c4c7c.js", "admin/js/vendor/select2/i18n/sr.js": "admin/js/vendor/select2/i18n/sr.5ed85a48f483.js", "admin/js/vendor/select2/i18n/sv.js": "admin/js/vendor/select2/i18n/sv.7a9c2f71e777.js", "admin/js/vendor/select2/i18n/th.js": "admin/js/vendor/select2/i18n/th.f38c20b0221b.js", "admin/js/vendor/select2/i18n/tk.js": "admin/js/vendor/select2/i18n/tk.7c572a68c78f.js", "admin/js/vendor/select2/i18n/tr.js": "admin/js/vendor/select2/i18n/tr.b5a0643d1545.js", "admin/js/vendor/select2/i18n/uk.js": "admin/js/vendor/select2/i18n/uk.8cede7f4803c.js", "admin/js/vendor/select2/i18n/vi.js": "admin/js/vendor/select2/i18n/vi.097a5b75b3e1.js", "admin/js/vendor/select2/i18n/zh-CN.js": "admin/js/vendor/select2/i18n/zh-CN.2cff662ec5f9.js", "admin/js/vendor/select2/i18n/zh-TW.js": "admin/js/vendor/select2/i18n/zh-TW.04554a227c2b.js", "admin/css/vendor/select2/LICENSE-SELECT2.md": "admin\\css\\vendor\\select2\\LICENSE-SELECT2.f94142512c91.md", "admin/css/vendor/select2/select2.css": "admin/css/vendor/select2/select2.a2194c262648.css", "admin/css/vendor/select2/select2.min.css": "admin/css/vendor/select2/select2.min.9f54e6414f87.css", "admin/js/vendor/jquery/jquery.js": "admin/js/vendor/jquery/jquery.2849239b95f5.js", "admin/js/vendor/jquery/jquery.min.js": "admin/js/vendor/jquery/jquery.min.8fb8fee4fcc3.js", "admin/js/vendor/jquery/LICENSE.txt": "admin\\js\\vendor\\jquery\\LICENSE.de877aa6d744.txt", "admin/js/vendor/select2/LICENSE.md": "admin\\js\\vendor\\select2\\LICENSE.f94142512c91.md", "admin/js/vendor/select2/select2.full.js": "admin/js/vendor/select2/select2.full.c2afdeda3058.js", "admin/js/vendor/select2/select2.full.min.js": "admin/js/vendor/select2/select2.full.min.fcd7500d8e13.js", "admin/js/vendor/xregexp/LICENSE.txt": "admin\\js\\vendor\\xregexp\\LICENSE.bf79e414957a.txt", "admin/js/vendor/xregexp/xregexp.js": "admin/js/vendor/xregexp/xregexp.efda034b9537.js", "admin/js/vendor/xregexp/xregexp.min.js": "admin/js/vendor/xregexp/xregexp.min.b0439563a5d3.js", "admin/img/gis/move_vertex_off.svg": "admin\\img\\gis\\move_vertex_off.7a23bf31ef8a.svg", "admin/img/gis/move_vertex_on.svg": "admin\\img\\gis\\move_vertex_on.0047eba25b67.svg", "admin/js/admin/DateTimeShortcuts.js": "admin/js/admin/DateTimeShortcuts.300591891b2b.js", "admin/js/admin/RelatedObjectLookups.js": "admin/js/admin/RelatedObjectLookups.de5309ac06dd.js", "fonts/Mont/Mont-Black.eot": "fonts\\Mont\\Mont-Black.c0d37de312ec.eot", "fonts/Mont/Mont-Black.ttf": "fonts\\Mont\\Mont-Black.cd8ca858f4c8.ttf", "fonts/Mont/Mont-Black.woff": "fonts\\Mont\\Mont-Black.98fcfaaeb28e.woff", "fonts/Mont/Mont-Black.woff2": "fonts\\Mont\\Mont-Black.0efaaa70d268.woff2", "fonts/Mont/Mont-BlackItalic.eot": "fonts\\Mont\\Mont-BlackItalic.7609929bfb43.eot", "fonts/Mont/Mont-BlackItalic.ttf": "fonts\\Mont\\Mont-BlackItalic.e49be7a1c7dc.ttf", "fonts/Mont/Mont-BlackItalic.woff": "fonts\\Mont\\Mont-BlackItalic.0f8577a616ec.woff", "fonts/Mont/Mont-BlackItalic.woff2": "fonts\\Mont\\Mont-BlackItalic.f70ae4e89f99.woff2", "fonts/Mont/Mont-Bold.eot": "fonts\\Mont\\Mont-Bold.1e9cca3a292f.eot", "fonts/Mont/Mont-Bold.ttf": "fonts\\Mont\\Mont-Bold.efd54e736e9b.ttf", "fonts/Mont/Mont-Bold.woff": "fonts\\Mont\\Mont-Bold.5660663cd1d5.woff", "fonts/Mont/Mont-Bold.woff2": "fonts\\Mont\\Mont-Bold.181bbbbbfda9.woff2", "fonts/Mont/Mont-BoldItalic.eot": "fonts\\Mont\\Mont-BoldItalic.a08b96f8de86.eot", "fonts/Mont/Mont-BoldItalic.ttf": "fonts\\Mont\\Mont-BoldItalic.b3309b41fe10.ttf", "fonts/Mont/Mont-BoldItalic.woff": "fonts\\Mont\\Mont-BoldItalic.a81daeaf36be.woff", "fonts/Mont/Mont-BoldItalic.woff2": "fonts\\Mont\\Mont-BoldItalic.ee0146576b53.woff2", "fonts/Mont/Mont-ExtraLight.eot": "fonts\\Mont\\Mont-ExtraLight.62deef703548.eot", "fonts/Mont/Mont-ExtraLight.ttf": "fonts\\Mont\\Mont-ExtraLight.179c8ebf4b56.ttf", "fonts/Mont/Mont-ExtraLight.woff": "fonts\\Mont\\Mont-ExtraLight.64b4d4ced84a.woff", "fonts/Mont/Mont-ExtraLight.woff2": "fonts\\Mont\\Mont-ExtraLight.2580442e650b.woff2", "fonts/Mont/Mont-ExtraLightItalic.eot": "fonts\\Mont\\Mont-ExtraLightItalic.a53f5c07e7c4.eot", "fonts/Mont/Mont-ExtraLightItalic.ttf": "fonts\\Mont\\Mont-ExtraLightItalic.412a2001e3cd.ttf", "fonts/Mont/Mont-ExtraLightItalic.woff": "fonts\\Mont\\Mont-ExtraLightItalic.e1f7753d896b.woff", "fonts/Mont/Mont-ExtraLightItalic.woff2": "fonts\\Mont\\Mont-ExtraLightItalic.c377eda56664.woff2", "fonts/Mont/Mont-Heavy.eot": "fonts\\Mont\\Mont-Heavy.225714cf8c53.eot", "fonts/Mont/Mont-Heavy.ttf": "fonts\\Mont\\Mont-Heavy.77e839f73803.ttf", "fonts/Mont/Mont-Heavy.woff": "fonts\\Mont\\Mont-Heavy.b4c3eda62a8c.woff", "fonts/Mont/Mont-Heavy.woff2": "fonts\\Mont\\Mont-Heavy.e82ce7e578ce.woff2", "fonts/Mont/Mont-HeavyItalic.eot": "fonts\\Mont\\Mont-HeavyItalic.d9fcfc701ace.eot", "fonts/Mont/Mont-HeavyItalic.ttf": "fonts\\Mont\\Mont-HeavyItalic.2e4c253f5d2d.ttf", "fonts/Mont/Mont-HeavyItalic.woff": "fonts\\Mont\\Mont-HeavyItalic.2cbe24962314.woff", "fonts/Mont/Mont-HeavyItalic.woff2": "fonts\\Mont\\Mont-HeavyItalic.17c1d13eed91.woff2", "fonts/Mont/Mont-Light.eot": "fonts\\Mont\\Mont-Light.446a23f9b23d.eot", "fonts/Mont/Mont-Light.ttf": "fonts\\Mont\\Mont-Light.b2eac4c24494.ttf", "fonts/Mont/Mont-Light.woff": "fonts\\Mont\\Mont-Light.d203b37c2376.woff", "fonts/Mont/Mont-Light.woff2": "fonts\\Mont\\Mont-Light.a2d8c87cdfd1.woff2", "fonts/Mont/Mont-LightItalic.eot": "fonts\\Mont\\Mont-LightItalic.210093c0700f.eot", "fonts/Mont/Mont-LightItalic.ttf": "fonts\\Mont\\Mont-LightItalic.4be1cebcde05.ttf", "fonts/Mont/Mont-LightItalic.woff": "fonts\\Mont\\Mont-LightItalic.905e36985e8e.woff", "fonts/Mont/Mont-LightItalic.woff2": "fonts\\Mont\\Mont-LightItalic.6a50db728c0c.woff2", "fonts/Mont/Mont-Regular.eot": "fonts\\Mont\\Mont-Regular.adcc201887fc.eot", "fonts/Mont/Mont-Regular.ttf": "fonts\\Mont\\Mont-Regular.abb74a597efa.ttf", "fonts/Mont/Mont-Regular.woff": "fonts\\Mont\\Mont-Regular.31fcd73a761b.woff", "fonts/Mont/Mont-Regular.woff2": "fonts\\Mont\\Mont-Regular.0dc474551d0e.woff2", "fonts/Mont/Mont-RegularItalic.eot": "fonts\\Mont\\Mont-RegularItalic.6bf85482ef84.eot", "fonts/Mont/Mont-RegularItalic.ttf": "fonts\\Mont\\Mont-RegularItalic.46f5a513b6dc.ttf", "fonts/Mont/Mont-RegularItalic.woff": "fonts\\Mont\\Mont-RegularItalic.606c9ba74430.woff", "fonts/Mont/Mont-RegularItalic.woff2": "fonts\\Mont\\Mont-RegularItalic.d5737d6e9fcd.woff2", "fonts/Mont/Mont-SemiBold.eot": "fonts\\Mont\\Mont-SemiBold.8263612bc8e9.eot", "fonts/Mont/Mont-SemiBold.ttf": "fonts\\Mont\\Mont-SemiBold.5cf16df9fb7a.ttf", "fonts/Mont/Mont-SemiBold.woff": "fonts\\Mont\\Mont-SemiBold.085d0f1b0a3b.woff", "fonts/Mont/Mont-SemiBold.woff2": "fonts\\Mont\\Mont-SemiBold.4ba0ced3282c.woff2", "fonts/Mont/Mont-SemiBoldItalic.eot": "fonts\\Mont\\Mont-SemiBoldItalic.ae6d69768850.eot", "fonts/Mont/Mont-SemiBoldItalic.ttf": "fonts\\Mont\\Mont-SemiBoldItalic.6cf32c234626.ttf", "fonts/Mont/Mont-SemiBoldItalic.woff": "fonts\\Mont\\Mont-SemiBoldItalic.96122e9cdf0c.woff", "fonts/Mont/Mont-SemiBoldItalic.woff2": "fonts\\Mont\\Mont-SemiBoldItalic.f18b40d7e3e2.woff2", "fonts/Mont/Mont-Thin.eot": "fonts\\Mont\\Mont-Thin.f9f9889ada62.eot", "fonts/Mont/Mont-Thin.ttf": "fonts\\Mont\\Mont-Thin.afeebec3ed59.ttf", "fonts/Mont/Mont-Thin.woff": "fonts\\Mont\\Mont-Thin.f336ce827c19.woff", "fonts/Mont/Mont-Thin.woff2": "fonts\\Mont\\Mont-Thin.71e76486be57.woff2", "fonts/Mont/Mont-ThinItalic.eot": "fonts\\Mont\\Mont-ThinItalic.bb2c80ca00c5.eot", "fonts/Mont/Mont-ThinItalic.ttf": "fonts\\Mont\\Mont-ThinItalic.1c6dd4bd2b13.ttf", "fonts/Mont/Mont-ThinItalic.woff": "fonts\\Mont\\Mont-ThinItalic.f36585076bec.woff", "fonts/Mont/Mont-ThinItalic.woff2": "fonts\\Mont\\Mont-ThinItalic.d3a2c329e056.woff2", "img/advantages/1.png": "img\\advantages\\1.cccb0a2fcf78.png", "img/advantages/2.png": "img\\advantages\\2.6caa8fd98359.png", "img/advantages/3.png": "img\\advantages\\3.e9939ca4daaa.png", "img/advantages2/010-organization-chart.png": "img\\advantages2\\010-organization-chart.a9e40c01c874.png", "img/advantages2/astronaut.png": "img\\advantages2\\astronaut.ed94d3d9d3f4.png", "img/advantages2/certificate.png": "img\\advantages2\\certificate.294859b68ff8.png", "img/advantages2/fountain.png": "img\\advantages2\\fountain.82be30f3cb72.png", "img/advantages2/growth.png": "img\\advantages2\\growth.2116071a8b9c.png", "img/advantages2/online.png": "img\\advantages2\\online.9b3c15bdcbeb.png", "img/gallery/1.jpg": "img\\gallery\\1.006e964e988a.jpg", "img/gallery/2.jpg": "img\\gallery\\2.4d5e52488f22.jpg", "img/gallery/3.jpg": "img\\gallery\\3.2e35b7842d5f.jpg", "img/gallery/4.jpg": "img\\gallery\\4.97443c47c0d5.jpg", "img/infographic/1.png": "img\\infographic\\1.4f2131a66731.png", "img/infographic/2.png": "img\\infographic\\2.8a5b18dcd37a.png", "img/infographic/3.png": "img\\infographic\\3.b969a540686e.png", "img/infographic/4.png": "img\\infographic\\4.a4088af889ae.png", "img/socs/fb.png": "img\\socs\\fb.5e05561585a9.png", "img/socs/insta.png": "img\\socs\\insta.6e6d70e9f383.png", "img/socs/whatsapp.png": "img\\socs\\whatsapp.616ca2002cf6.png", "img/speakers/birukova.jpg": "img\\speakers\\birukova.e3098b39ee33.jpg", "img/speakers/cehovoy.jpg": "img\\speakers\\cehovoy.60085d8c3317.jpg", "img/speakers/domenko.jpg": "img\\speakers\\domenko.931cdac4fc70.jpg", "img/speakers/esengeldin.jpg": "img\\speakers\\esengeldin.1124d491a2df.jpg", "img/speakers/golikov.jpg": "img\\speakers\\golikov.a8cc625baf3e.jpg", "img/speakers/hamitov.jpg": "img\\speakers\\hamitov.146c5ba0a83f.jpg", "img/speakers/li.jpg": "img\\speakers\\li.43ecd651b220.jpg", "img/speakers/nurtazina.jpg": "img\\speakers\\nurtazina.889cf8139720.jpg", "admin/css/autocomplete.css": "admin/css/autocomplete.4a81fc4242d0.css", "admin/css/base.css": "admin/css/base.01580fff1759.css", "admin/css/changelists.css": "admin/css/changelists.ae46354f4e80.css", "admin/css/dark_mode.css": "admin/css/dark_mode.4e3d1504ca81.css", "admin/css/dashboard.css": "admin/css/dashboard.be83f13e4369.css", "admin/css/fonts.css": "admin/css/fonts.168bab448fee.css", "admin/css/forms.css": "admin/css/forms.c192d1ec6902.css", "admin/css/login.css": "admin/css/login.586129c60a93.css", "admin/css/nav_sidebar.css": "admin/css/nav_sidebar.30423191f399.css", "admin/css/responsive.css": "admin/css/responsive.02281633b5f1.css", "admin/css/responsive_rtl.css": "admin/css/responsive_rtl.e13ae754cceb.css", "admin/css/rtl.css": "admin/css/rtl.8473f45bd49b.css", "admin/css/widgets.css": "admin/css/widgets.00318bc424d3.css", "admin/fonts/LICENSE.txt": "admin\\fonts\\LICENSE.d273d63619c9.txt", "admin/fonts/README.txt": "admin\\fonts\\README.ab99e6b541ea.txt", "admin/fonts/Roboto-Bold-webfont.woff": "admin\\fonts\\Roboto-Bold-webfont.50d75e48e0a3.woff", "admin/fonts/Roboto-Light-webfont.woff": "admin\\fonts\\Roboto-Light-webfont.c73eb1ceba33.woff", "admin/fonts/Roboto-Regular-webfont.woff": "admin\\fonts\\Roboto-Regular-webfont.35b07eb2f871.woff", "admin/img/calendar-icons.svg": "admin\\img\\calendar-icons.39b290681a8b.svg", "admin/img/icon-addlink.svg": "admin\\img\\icon-addlink.d519b3bab011.svg", "admin/img/icon-alert.svg": "admin\\img\\icon-alert.034cc7d8a67f.svg", "admin/img/icon-calendar.svg": "admin\\img\\icon-calendar.ac7aea671bea.svg", "admin/img/icon-changelink.svg": "admin\\img\\icon-changelink.18d2fd706348.svg", "admin/img/icon-clock.svg": "admin\\img\\icon-clock.e1d4dfac3f2b.svg", "admin/img/icon-deletelink.svg": "admin\\img\\icon-deletelink.564ef9dc3854.svg", "admin/img/icon-no.svg": "admin\\img\\icon-no.439e821418cd.svg", "admin/img/icon-unknown-alt.svg": "admin\\img\\icon-unknown-alt.81536e128bb6.svg", "admin/img/icon-unknown.svg": "admin\\img\\icon-unknown.a18cb4398978.svg", "admin/img/icon-viewlink.svg": "admin\\img\\icon-viewlink.41eb31f7826e.svg", "admin/img/icon-yes.svg": "admin\\img\\icon-yes.d2f9f035226a.svg", "admin/img/inline-delete.svg": "admin\\img\\inline-delete.fec1b761f254.svg", "admin/img/LICENSE": "admin\\img\\LICENSE.2c54f4e1ca1c", "admin/img/README.txt": "admin\\img\\README.a70711a38d87.txt", "admin/img/search.svg": "admin\\img\\search.7cf54ff789c6.svg", "admin/img/selector-icons.svg": "admin\\img\\selector-icons.b4555096cea2.svg", "admin/img/sorting-icons.svg": "admin\\img\\sorting-icons.3a097b59f104.svg", "admin/img/tooltag-add.svg": "admin\\img\\tooltag-add.e59d620a9742.svg", "admin/img/tooltag-arrowright.svg": "admin\\img\\tooltag-arrowright.bbfb788a849e.svg", "admin/js/actions.js": "admin/js/actions.eac7e3441574.js", "admin/js/autocomplete.js": "admin/js/autocomplete.01591ab27be7.js", "admin/js/calendar.js": "admin/js/calendar.f8a5d055eb33.js", "admin/js/cancel.js": "admin/js/cancel.ecc4c5ca7b32.js", "admin/js/change_form.js": "admin/js/change_form.9d8ca4f96b75.js", "admin/js/collapse.js": "admin/js/collapse.f84e7410290f.js", "admin/js/core.js": "admin/js/core.5d6b384a08b5.js", "admin/js/filters.js": "admin/js/filters.295a9d3d8b6a.js", "admin/js/inlines.js": "admin/js/inlines.22d4d93c00b4.js", "admin/js/jquery.init.js": "admin/js/jquery.init.b7781a0897fc.js", "admin/js/nav_sidebar.js": "admin/js/nav_sidebar.36a64ecb39ed.js", "admin/js/popup_response.js": "admin/js/popup_response.c6cc78ea5551.js", "admin/js/prepopulate.js": "admin/js/prepopulate.bd2361dfd64d.js", "admin/js/prepopulate_init.js": "admin/js/prepopulate_init.6cac7f3105b8.js", "admin/js/SelectBox.js": "admin/js/SelectBox.8161741c7647.js", "admin/js/SelectFilter2.js": "admin/js/SelectFilter2.3f53e33c88d6.js", "admin/js/urlify.js": "admin/js/urlify.25cc3eac8123.js", "css/bootstrap.min.css": "css/bootstrap.min.d41d8cd98f00.css", "css/modal.css": "css/modal.46082ded4a38.css", "css/style.css": "css/style.ed2333759e47.css", "css/style.css.map": "css\\style.css.6516174c5556.map", "css/style.min.css": "css/style.min.460b92f62946.css", "css/style.min.css.map": "css\\style.min.css.022364e5f7e6.map", "css/style.scss": "css\\style.226a5cb83a59.scss", "css/style2.css": "css/style2.6b48b7d9d83e.css", "img/about-illustration.jpg": "img\\about-illustration.e113c93b55c7.jpg", "img/booking_bg.jpg": "img\\booking_bg.436728d125af.jpg", "img/favicon.ico": "img\\favicon.08e24043a68f.ico", "img/logo.png": "img\\logo.3a40977f97e1.png", "img/well-bg.jpg": "img\\well-bg.26525b9a61dc.jpg", "js/app.js": "js/app.96d4ecb3839c.js", "js/app.js.map": "js\\app.js.de0ba0229a41.map", "js/form.js": "js/form.308188dc8a9e.js", "js/index.js": "js/index.5194f45dbd04.js", "js/materialize.min.js": "js/materialize.min.5dcfc8944ed3.js", "js/modal.js": "js/modal.0004242a0c24.js"}, "version": "1.0"}